Workbook

Sheet README
A1: BBVA Culture Index
A3: What is this file? | B3: A practice (“pilot”) dataset we built to test our Culture Index before any real data exist. It lets us check that the index formula, the scaling, and our statistical models all work end-to-end.
A4: What is real and what is invented? | B4: Almost everything here is GENERATED. None of the employees are real people and nothing here describes BBVA’s actual culture. The only real numbers are on the sheet ‘lseg_observed’ and in a few cells marked with a red source comment, those come from public Refinitiv data on Spanish banks.
A6: The three scenarios (the key idea) | B6: We invented 500 fictional BBVA Spain employees — each with a region, a department, gender, tenure, and so on. Then we “surveyed” the same 500 people three times, each time pretending the company culture was different: A-Strong (a great culture), B-Average (a normal culture, tuned to match the public numbers we know about BBVA, like its 11.8% staff turnover), and C-Weak (a bad culture). The four peer banks (Santander, CaixaBank, Sabadell, Bankinter) were invented once, as the comparison group (“Benchmark”).
A7: Why three scenarios? | B7: It is our quality check. If the index is built correctly, the Strong world must score clearly higher than the Average world, and the Average clearly higher than the Weak one, and it does (about 85 vs 48 vs 13 out of 100). The models are estimated only on B-Average + Benchmark; A and C just prove the index reacts the right way.
A9: How the index works, in one sentence | B9: Each indicator (e.g. eNPS, turnover) is rescaled between 0 = worst in the peer group and 1 = best in the peer group; “bad” indicators like turnover are flipped so higher always means better; the five dimension scores are then combined with weights into one number from 0 to 100.
A10: Everything is live | B10: The scores are Excel formulas, not pasted numbers. If you change a weight (blue cells on ‘scaling_params’) or any input value, every index in the file recalculates by itself. When our real survey answers arrive, we can paste them into the same columns and the whole pipeline runs on real data.
A12: What each sheet contains
A13: codebook | B13: what every column means, its range, where it comes from, and which model uses it.
A14: employee_year | B14: The main table. One row = one employee in one year. 3,800 rows = 500 BBVA employees × 2 years × 3 scenarios + 4 peer banks × 100 employees × 2 years. The last columns compute each person’s dimension scores and Culture Index.
A15: scaling_params | B15: The “settings” sheet: the best/worst values used for rescaling, and the five dimension weights (blue = you can change them).
A16: dept_year | B16: The same data summarized per department and year — used for the innovation model.
A17: bank_year | B17: One row per bank per year: the average index, plus customer-side measures (brand trust, customer NPS) kept OUTSIDE the index on purpose, plus real 2025 financials from Refinitiv.
A18: scenario_summary | B18: A small table comparing the three invented worlds side by side, the quality check described above.
A19: lseg_observed | B19: The REAL public data: Refinitiv Public Companies dataset figures for BBVA and Spanish peer banks.
A21: One rule to remember | B21: Any result computed from the invented part of this file is only a demonstration of the method. It says nothing about BBVA’s real culture.
A22: Technical footnote | B22: Generated in Python (NumPy, random seed 42, fully reproducible). Employee IDs are anonymous hash codes, identical across the three scenario copies of the same fictional person.

Sheet codebook
A1: Column | B1: What it means (plain language) | C1: Part of the index? | D1: Type | E1: Range | F1: Good direction | G1: Where it comes from | H1: Which model uses it
A2: emp_id | B2: Anonymous code for one fictional employee. The same code appears in all three scenarios, because it is the same invented person “surveyed” three times. | C2: No – identifier | D2: Text | E2: 8 characters | F2: — | G2: Generated | H2: All
A3: bank | B3: Which bank the person works for. | C3: No – identifier | D3: Category | E3: BBVA + 4 Spanish peers | F3: — | G3: Generated | H3: All
A4: region | B4: Spanish region of the workplace. | C4: No – identifier | D4: Category | E4: Madrid / Catalunya / Andalucia / Pais Vasco / C. Valenciana | F4: — | G4: Generated | H4: Model 5
A5: dept | B5: Department. | C5: No – identifier | D5: Category | E5: Retail / Corporate / Digital / Risk / Operations | F5: — | G5: Generated | H5: Models 1, 3, 5
A6: year | B6: Year of the observation. | C6: No – control | D6: Number | E6: 2024–2025 | F6: — | G6: Generated | H6: All
A7: gender | B7: Gender. | C7: No – control | D7: Category | E7: F / M | F7: — | G7: Survey question (simulated for now) | H7: Background control
A8: tenure_band | B8: How long the person has worked at the bank (in bands, so nobody is identifiable). | C8: No – control | D8: Category | E8: 0-2 / 3-5 / 6-10 / 10+ years | F8: — | G8: Survey question (simulated for now) | H8: Background control
A9: comp_band | B9: Pay level in 5 broad bands (1 = lowest). | C9: No – control | D9: Number | E9: 1–5 | F9: — | G9: Survey question (simulated for now) | H9: Control (separates pay effects from culture)
A10: unemp_r | B10: Unemployment rate in the person’s region — captures the local job market. | C10: No – control | D10: Number | E10: % (approx. INE) | F10: — | G10: Public statistics | H10: Control
A11: exit | B11: Did the person voluntarily leave the bank that year? 1 = yes, 0 = no. | C11: No – outcome | D11: 0 or 1 | E11: 0/1 | F11: — | G11: Would come from HR; simulated here | H11: Model 1 (the thing we predict)
A12: comply_inc | B12: Compliance incidents per 100 employees in the department — rule-breaking events. | C12: Yes – Ethics | D12: Number | E12: 0–12 | F12: Lower is better (flipped) | G12: Would come from HR; simulated here | H12: Index
... A32: benchmark_flag | B32: 1 = row belongs to the “real-world” base case used in the models (B-Average + Benchmark); 0 = Strong/Weak test copies. | C32: No – design | D32: 0 or 1 | E32: 0/1 | F32: — | G32: Formula | H32: Scaling; model filters
B33: Direction legend: + = higher value indicates stronger culture; − = reverse-coded before entering the index.
B34: An identifier is used to recognize or group records, but it is not used to measure culture.
B35: A control variable is included in statistical models to account for other factors that might influence the results.
B36: An outcome variable is the thing you are trying to explain, predict, or improve.
B37: A design variable describes the structure of the study or helps define the research setup.

Sheet employee_year
A1: emp_id | B1: bank | C1: region | D1: dept | E1: year | F1: gender | G1: tenure_band | H1: comp_band | I1: unemp_r | J1: exit | K1: comply_inc | L1: ethics_sc | M1: enps | N1: pay_equity | O1: particip_rate | P1: absent_rate | Q1: turnover_rate | R1: mob_rate | S1: trust_360 | T1: psych_safety | U1: ideas_100fte | V1: training_compl | W1: key | X1: ethics_dim | Y1: satisf_dim | Z1: engage_dim | AA1: empexp_dim | AB1: innov_dim | AC1: culture_idx | AD1: scenario | AE1: benchmark_flag
A2: 00577edd | B2: BBVA | C2: Andalucia | D2: Operations | E2: 2024 | F2: M | G2: 0-2 | H2: 4 | I2: 15.8 | J2: 0 | K2: 1.1 | L2: 6.4 | M2: 16 | N2: 0.83 | O2: 77.5 | P2: 5.8 | Q2: 9.9 | R2: 17.5 | S2: 4.3 | T2: 3.6 | U2: 2.8 | V2: 78.2 | W2: =AD2&"|"&B2&"|"&D2&"|"&E2 -> A-Strong|BBVA|Operations|2024 | X2: =(MAX(0,MIN(1,1-(K2-scaling_params!$B$2)/(scaling_params!$C$2-scaling_params!$B$2)))+MAX(0,MIN(1,(L2-scaling_params!$B$3)/(scaling_params!$C$3-scaling_params!$B$3))))/2 -> 0.73333333 | Y2: =(MAX(0,MIN(1,(M2-scaling_params!$B$4)/(scaling_params!$C$4-scaling_params!$B$4)))+MAX(0,MIN(1,(N2-scaling_params!$B$5)/(scaling_params!$C$5-scaling_params!$B$5))))/2 -> 0.625 | Z2: =(MAX(0,MIN(1,(O2-scaling_params!$B$6)/(scaling_params!$C$6-scaling_params!$B$6)))+MAX(0,MIN(1,1-(P2-scaling_params!$B$7)/(scaling_params!$C$7-scaling_params!$B$7)))+MAX(0,MIN(1,(T2-scaling_params!$B$11)/(scaling_params!$C$11-scaling_params!$B$11))))/3 -> 0.83963964 | AA2: =(MAX(0,MIN(1,1-(Q2-scaling_params!$B$8)/(scaling_params!$C$8-scaling_params!$B$8)))+MAX(0,MIN(1,(R2-scaling_params!$B$9)/(scaling_params!$C$9-scaling_params!$B$9)))+MAX(0,MIN(1,(S2-scaling_params!$B$10)/(scaling_params!$C$10-scaling_params!$B$10))))/3 -> 0.89761727 | AB2: =(MAX(0,MIN(1,(U2-scaling_params!$B$12)/(scaling_params!$C$12-scaling_params!$B$12)))+MAX(0,MIN(1,(V2-scaling_params!$B$13)/(scaling_params!$C$13-scaling_params!$B$13))))/2 -> 0.76636364 | AC2: =(scaling_params!$G$2*X2+scaling_params!$G$3*Y2+scaling_params!$G$4*Z2+scaling_params!$G$5*AA2+scaling_params!$G$6*AB2)*100 -> 76.49352 | AD2: A-Strong | AE2: =IF(OR(AD2="B-Average",AD2="Benchmark"),1,0) -> 0
A3: 00577edd | B3: BBVA | C3: Andalucia | D3: Operations | E3: 2025 | F3: M | G3: 0-2 | H3: 4 | I3: 15.2 | J3: 0 | K3: 0 | L3: 7.4 | M3: 15 | N3: 0.79 | O3: 83.2 | P3: 5 | Q3: 10.1 | R3: 16.7 | S3: 3.6 | T3: 3.3 | U3: 3.6 | V3: 76.8 | W3: =AD3&"|"&B3&"|"&D3&"|"&E3 -> A-Strong|BBVA|Operations|2025 | X3: =(MAX(0,MIN(1,1-(K3-scaling_params!$B$2)/(scaling_params!$C$2-scaling_params!$B$2)))+MAX(0,MIN(1,(L3-scaling_params!$B$3)/(scaling_params!$C$3-scaling_params!$B$3))))/2 -> 0.82352941 | Y3: =(MAX(0,MIN(1,(M3-scaling_params!$B$4)/(scaling_params!$C$4-scaling_params!$B$4)))+MAX(0,MIN(1,(N3-scaling_params!$B$5)/(scaling_params!$C$5-scaling_params!$B$5))))/2 -> 0.5702381 | Z3: =(MAX(0,MIN(1,(O3-scaling_params!$B$6)/(scaling_params!$C$6-scaling_params!$B$6)))+MAX(0,MIN(1,1-(P3-scaling_params!$B$7)/(scaling_params!$C$7-scaling_params!$B$7)))+MAX(0,MIN(1,(T3-scaling_params!$B$11)/(scaling_params!$C$11-scaling_params!$B$11))))/3 -> 0.83809524 | AA3: =(MAX(0,MIN(1,1-(Q3-scaling_params!$B$8)/(scaling_params!$C$8-scaling_params!$B$8)))+MAX(0,MIN(1,(R3-scaling_params!$B$9)/(scaling_params!$C$9-scaling_params!$B$9)))+MAX(0,MIN(1,(S3-scaling_params!$B$10)/(scaling_params!$C$10-scaling_params!$B$10))))/3 -> 0.79523455 | AB3: =(MAX(0,MIN(1,(U3-scaling_params!$B$12)/(scaling_params!$C$12-scaling_params!$B$12)))+MAX(0,MIN(1,(V3-scaling_params!$B$13)/(scaling_params!$C$13-scaling_params!$B$13))))/2 -> 0.80363636 | AC3: =(scaling_params!$G$2*X3+scaling_params!$G$3*Y3+scaling_params!$G$4*Z3+scaling_params!$G$5*AA3+scaling_params!$G$6*AB3)*100 -> 75.927812 | AD3: A-Strong | AE3: =IF(OR(AD3="B-Average",AD3="Benchmark"),1,0) -> 0
A4: 00ce0f00 | B4: BBVA | C4: Andalucia | D4: Risk | E4: 2024 | F4: F | G4: 10+ | H4: 4 | I4: 15.8 | J4: 0 | K4: 0.2 | L4: 8 | M4: 25 | N4: 0.96 | O4: 82.1 | P4: 5.1 | Q4: 12.5 | R4: 18.1 | S4: 4.7 | T4: 4 | U4: 2.3 | V4: 75.2 | W4: =AD4&"|"&B4&"|"&D4&"|"&E4 -> A-Strong|BBVA|Risk|2024 | X4: =(MAX(0,MIN(1,1-(K4-scaling_params!$B$2)/(scaling_params!$C$2-scaling_params!$B$2)))+MAX(0,MIN(1,(L4-scaling_params!$B$3)/(scaling_params!$C$3-scaling_params!$B$3))))/2 -> 0.86764706 | Y4: =(MAX(0,MIN(1,(M4-scaling_params!$B$4)/(scaling_params!$C$4-scaling_params!$B$4)))+MAX(0,MIN(1,(N4-scaling_params!$B$5)/(scaling_params!$C$5-scaling_params!$B$5))))/2 -> 0.83035714 | Z4: =(MAX(0,MIN(1,(O4-scaling_params!$B$6)/(scaling_params!$C$6-scaling_params!$B$6)))+MAX(0,MIN(1,1-(P4-scaling_params!$B$7)/(scaling_params!$C$7-scaling_params!$B$7)))+MAX(0,MIN(1,(T4-scaling_params!$B$11)/(scaling_params!$C$11-scaling_params!$B$11))))/3 -> 0.9047619 | AA4: =(MAX(0,MIN(1,1-(Q4-scaling_params!$B$8)/(scaling_params!$C$8-scaling_params!$B$8)))+MAX(0,MIN(1,(R4-scaling_params!$B$9)/(scaling_params!$C$9-scaling_params!$B$9)))+MAX(0,MIN(1,(S4-scaling_params!$B$10)/(scaling_params!$C$10-scaling_params!$B$10))))/3 -> 0.92805851 | AB4: =(MAX(0,MIN(1,(U4-scaling_params!$B$12)/(scaling_params!$C$12-scaling_params!$B$12)))+MAX(0,MIN(1,(V4-scaling_params!$B$13)/(scaling_params!$C$13-scaling_params!$B$13))))/2 -> 0.61409091 | AC4: =(scaling_params!$G$2*X4+scaling_params!$G$3*Y4+scaling_params!$G$4*Z4+scaling_params!$G$5*AA4+scaling_params!$G$6*AB4)*100 -> 84.745106 | AD4: A-Strong | AE4: =IF(OR(AD4="B-Average",AD4="Benchmark"),1,0) -> 0
A5: 00ce0f00 | B5: BBVA | C5: Andalucia | D5: Risk | E5: 2025 | F5: F | G5: 10+ | H5: 4 | I5: 15.2 | J5: 0 | K5: 0 | L5: 7.8 | M5: 46 | N5: 0.88 | O5: 82.8 | P5: 4.9 | Q5: 8.3 | R5: 17 | S5: 4 | T5: 4.1 | U5: 5.1 | V5: 80.7 | W5: =AD5&"|"&B5&"|"&D5&"|"&E5 -> A-Strong|BBVA|Risk|2025 | X5: =(MAX(0,MIN(1,1-(K5-scaling_params!$B$2)/(scaling_params!$C$2-scaling_params!$B$2)))+MAX(0,MIN(1,(L5-scaling_params!$B$3)/(scaling_params!$C$3-scaling_params!$B$3))))/2 -> 0.85294118 | Y5: =(MAX(0,MIN(1,(M5-scaling_params!$B$4)/(scaling_params!$C$4-scaling_params!$B$4)))+MAX(0,MIN(1,(N5-scaling_params!$B$5)/(scaling_params!$C$5-scaling_params!$B$5))))/2 -> 0.83035714 | Z5: =(MAX(0,MIN(1,(O5-scaling_params!$B$6)/(scaling_params!$C$6-scaling_params!$B$6)))+MAX(0,MIN(1,1-(P5-scaling_params!$B$7)/(scaling_params!$C$7-scaling_params!$B$7)))+MAX(0,MIN(1,(T5-scaling_params!$B$11)/(scaling_params!$C$11-scaling_params!$B$11))))/3 -> 0.91428571 | AA5: =(MAX(0,MIN(1,1-(Q5-scaling_params!$B$8)/(scaling_params!$C$8-scaling_params!$B$8)))+MAX(0,MIN(1,(R5-scaling_params!$B$9)/(scaling_params!$C$9-scaling_params!$B$9)))+MAX(0,MIN(1,(S5-scaling_params!$B$10)/(scaling_params!$C$10-scaling_params!$B$10))))/3 -> 0.84710846 | AB5: =(MAX(0,MIN(1,(U5-scaling_params!$B$12)/(scaling_params!$C$12-scaling_params!$B$12)))+MAX(0,MIN(1,(V5-scaling_params!$B$13)/(scaling_params!$C$13-scaling_params!$B$13))))/2 -> 0.83909091 | AC5: =(scaling_params!$G$2*X5+scaling_params!$G$3*Y5+scaling_params!$G$4*Z5+scaling_params!$G$5*AA5+scaling_params!$G$6*AB5)*100 -> 85.853606 | AD5: A-Strong | AE5: =IF(OR(AD5="B-Average",AD5="Benchmark"),1,0) -> 0
A6: 02aa584e | B6: BBVA | C6: Andalucia | D6: Digital | E6: 2024 | F6: F | G6: 3-5 | H6: 3 | I6: 15.8 | J6: 0 | K6: 1.3 | L6: 7 | M6: 28 | N6: 0.78 | O6: 73.3 | P6: 4.6 | Q6: 12.9 | R6: 18.1 | S6: 4.5 | T6: 4.5 | U6: 2.7 | V6: 79 | W6: =AD6&"|"&B6&"|"&D6&"|"&E6 -> A-Strong|BBVA|Digital|2024 | X6: =(MAX(0,MIN(1,1-(K6-scaling_params!$B$2)/(scaling_params!$C$2-scaling_params!$B$2)))+MAX(0,MIN(1,(L6-scaling_params!$B$3)/(scaling_params!$C$3-scaling_params!$B$3))))/2 -> 0.74411765 | Y6: =(MAX(0,MIN(1,(M6-scaling_params!$B$4)/(scaling_params!$C$4-scaling_params!$B$4)))+MAX(0,MIN(1,(N6-scaling_params!$B$5)/(scaling_params!$C$5-scaling_params!$B$5))))/2 -> 0.61964286 | Z6: =(MAX(0,MIN(1,(O6-scaling_params!$B$6)/(scaling_params!$C$6-scaling_params!$B$6)))+MAX(0,MIN(1,1-(P6-scaling_params!$B$7)/(scaling_params!$C$7-scaling_params!$B$7)))+MAX(0,MIN(1,(T6-scaling_params!$B$11)/(scaling_params!$C$11-scaling_params!$B$11))))/3 -> 0.89462518 | AA6: =(MAX(0,MIN(1,1-(Q6-scaling_params!$B$8)/(scaling_params!$C$8-scaling_params!$B$8)))+MAX(0,MIN(1,(R6-scaling_params!$B$9)/(scaling_params!$C$9-scaling_params!$B$9)))+MAX(0,MIN(1,(S6-scaling_params!$B$10)/(scaling_params!$C$10-scaling_params!$B$10))))/3 -> 0.89329915 | AB6: =(MAX(0,MIN(1,(U6-scaling_params!$B$12)/(scaling_params!$C$12-scaling_params!$B$12)))+MAX(0,MIN(1,(V6-scaling_params!$B$13)/(scaling_params!$C$13-scaling_params!$B$13))))/2 -> 0.74863636 | AC6: =(scaling_params!$G$2*X6+scaling_params!$G$3*Y6+scaling_params!$G$4*Z6+scaling_params!$G$5*AA6+scaling_params!$G$6*AB6)*100 -> 77.628038 | AD6: A-Strong | AE6: =IF(OR(AD6="B-Average",AD6="Benchmark"),1,0) -> 0
A7: 02aa584e | B7: BBVA | C7: Andalucia | D7: Digital | E7: 2025 | F7: F | G7: 3-5 | H7: 3 | I7: 15.2 | J7: 0 | K7: 1.2 | L7: 5.8 | M7: 32 | N7: 0.91 | O7: 78.6 | P7: 4.2 | Q7: 12.7 | R7: 18.1 | S7: 4.7 | T7: 4 | U7: 3.7 | V7: 73.5 | W7: =AD7&"|"&B7&"|"&D7&"|"&E7 -> A-Strong|BBVA|Digital|2025 | X7: =(MAX(0,MIN(1,1-(K7-scaling_params!$B$2)/(scaling_params!$C$2-scaling_params!$B$2)))+MAX(0,MIN(1,(L7-scaling_params!$B$3)/(scaling_params!$C$3-scaling_params!$B$3))))/2 -> 0.67254902 | Y7: =(MAX(0,MIN(1,(M7-scaling_params!$B$4)/(scaling_params!$C$4-scaling_params!$B$4)))+MAX(0,MIN(1,(N7-scaling_params!$B$5)/(scaling_params!$C$5-scaling_params!$B$5))))/2 -> 0.80119048 | Z7: =(MAX(0,MIN(1,(O7-scaling_params!$B$6)/(scaling_params!$C$6-scaling_params!$B$6)))+MAX(0,MIN(1,1-(P7-scaling_params!$B$7)/(scaling_params!$C$7-scaling_params!$B$7)))+MAX(0,MIN(1,(T7-scaling_params!$B$11)/(scaling_params!$C$11-scaling_params!$B$11))))/3 -> 0.9047619 | AA7: =(MAX(0,MIN(1,1-(Q7-scaling_params!$B$8)/(scaling_params!$C$8-scaling_params!$B$8)))+MAX(0,MIN(1,(R7-scaling_params!$B$9)/(scaling_params!$C$9-scaling_params!$B$9)))+MAX(0,MIN(1,(S7-scaling_params!$B$10)/(scaling_params!$C$10-scaling_params!$B$10))))/3 -> 0.92048275 | AB7: =(MAX(0,MIN(1,(U7-scaling_params!$B$12)/(scaling_params!$C$12-scaling_params!$B$12)))+MAX(0,MIN(1,(V7-scaling_params!$B$13)/(scaling_params!$C$13-scaling_params!$B$13))))/2 -> 0.77363636 | AC7: =(scaling_params!$G$2*X7+scaling_params!$G$3*Y7+scaling_params!$G$4*Z7+scaling_params!$G$5*AA7+scaling_params!$G$6*AB7)*100 -> 81.224188 | AD7: A-Strong | AE7: =IF(OR(AD7="B-Average",AD7="Benchmark"),1,0) -> 0
A8: 0439eee0 | B8: BBVA | C8: Andalucia | D8: Retail | E8: 2024 | F8: M | G8: 10+ | H8: 2 | I8: 15.8 | J8: 0 | K8: 0.2 | L8: 8.5 | M8: 6 | N8: 0.85 | O8: 76.2 | P8: 4.6 | Q8: 11.9 | R8: 17.6 | S8: 4 | T8: 3.8 | U8: 3.5 | V8: 82.9 | W8: =AD8&"|"&B8&"|"&D8&"|"&E8 -> A-Strong|BBVA|Retail|2024 | X8: =(MAX(0,MIN(1,1-(K8-scaling_params!$B$2)/(scaling_params!$C$2-scaling_params!$B$2)))+MAX(0,MIN(1,(L8-scaling_params!$B$3)/(scaling_params!$C$3-scaling_params!$B$3))))/2 -> 0.90441176 | Y8: =(MAX(0,MIN(1,(M8-scaling_params!$B$4)/(scaling_params!$C$4-scaling_params!$B$4)))+MAX(0,MIN(1,(N8-scaling_params!$B$5)/(scaling_params!$C$5-scaling_params!$B$5))))/2 -> 0.60238095 | Z8: =(MAX(0,MIN(1,(O8-scaling_params!$B$6)/(scaling_params!$C$6-scaling_params!$B$6)))+MAX(0,MIN(1,1-(P8-scaling_params!$B$7)/(scaling_params!$C$7-scaling_params!$B$7)))+MAX(0,MIN(1,(T8-scaling_params!$B$11)/(scaling_params!$C$11-scaling_params!$B$11))))/3 -> 0.8758133 | AA8: =(MAX(0,MIN(1,1-(Q8-scaling_params!$B$8)/(scaling_params!$C$8-scaling_params!$B$8)))+MAX(0,MIN(1,(R8-scaling_params!$B$9)/(scaling_params!$C$9-scaling_params!$B$9)))+MAX(0,MIN(1,(S8-scaling_params!$B$10)/(scaling_params!$C$10-scaling_params!$B$10))))/3 -> 0.86106128 | AB8: =(MAX(0,MIN(1,(U8-scaling_params!$B$12)/(scaling_params!$C$12-scaling_params!$B$12)))+MAX(0,MIN(1,(V8-scaling_params!$B$13)/(scaling_params!$C$13-scaling_params!$B$13))))/2 -> 0.85909091 | AC8: =(scaling_params!$G$2*X8+scaling_params!$G$3*Y8+scaling_params!$G$4*Z8+scaling_params!$G$5*AA8+scaling_params!$G$6*AB8)*100 -> 81.283193 | AD8: A-Strong | AE8: =IF(OR(AD8="B-Average",AD8="Benchmark"),1,0) -> 0
A9: 0439eee0 | B9: BBVA | C9: Andalucia | D9: Retail | E9: 2025 | F9: M | G9: 10+ | H9: 2 | I9: 15.2 | J9: 0 | K9: 1.2 | L9: 6.1 | M9: 30 | N9: 0.85 | O9: 79.5 | P9: 6.5 | Q9: 9.6 | R9: 16.3 | S9: 4 | T9: 3.7 | U9: 3.5 | V9: 91.6 | W9: =AD9&"|"&B9&"|"&D9&"|"&E9 -> A-Strong|BBVA|Retail|2025 | X9: =(MAX(0,MIN(1,1-(K9-scaling_params!$B$2)/(scaling_params!$C$2-scaling_params!$B$2)))+MAX(0,MIN(1,(L9-scaling_params!$B$3)/(scaling_params!$C$3-scaling_params!$B$3))))/2 -> 0.69460784 | Y9: =(MAX(0,MIN(1,(M9-scaling_params!$B$4)/(scaling_params!$C$4-scaling_params!$B$4)))+MAX(0,MIN(1,(N9-scaling_params!$B$5)/(scaling_params!$C$5-scaling_params!$B$5))))/2 -> 0.71666667 | Z9: =(MAX(0,MIN(1,(O9-scaling_params!$B$6)/(scaling_params!$C$6-scaling_params!$B$6)))+MAX(0,MIN(1,1-(P9-scaling_params!$B$7)/(scaling_params!$C$7-scaling_params!$B$7)))+MAX(0,MIN(1,(T9-scaling_params!$B$11)/(scaling_params!$C$11-scaling_params!$B$11))))/3 -> 0.78610039 | AA9: =(MAX(0,MIN(1,1-(Q9-scaling_params!$B$8)/(scaling_params!$C$8-scaling_params!$B$8)))+MAX(0,MIN(1,(R9-scaling_params!$B$9)/(scaling_params!$C$9-scaling_params!$B$9)))+MAX(0,MIN(1,(S9-scaling_params!$B$10)/(scaling_params!$C$10-scaling_params!$B$10))))/3 -> 0.8175726 | AB9: =(MAX(0,MIN(1,(U9-scaling_params!$B$12)/(scaling_params!$C$12-scaling_params!$B$12)))+MAX(0,MIN(1,(V9-scaling_params!$B$13)/(scaling_params!$C$13-scaling_params!$B$13))))/2 -> 0.93818182 | AC9: =(scaling_params!$G$2*X9+scaling_params!$G$3*Y9+scaling_params!$G$4*Z9+scaling_params!$G$5*AA9+scaling_params!$G$6*AB9)*100 -> 77.098133 | AD9: A-Strong | AE9: =IF(OR(AD9="B-Average",AD9="Benchmark"),1,0) -> 0
A10: 08c01be8 | B10: BBVA | C10: Andalucia | D10: Operations | E10: 2024 | F10: F | G10: 0-2 | H10: 1 | I10: 15.8 | J10: 0 | K10: 1.1 | L10: 7.4 | M10: 24 | N10: 0.92 | O10: 77.5 | P10: 5.8 | Q10: 9.9 | R10: 17.5 | S10: 4.7 | T10: 4.6 | U10: 2.8 | V10: 74.3 | W10: =AD10&"|"&B10&"|"&D10&"|"&E10 -> A-Strong|BBVA|Operations|2024 | X10: =(MAX(0,MIN(1,1-(K10-scaling_params!$B$2)/(scaling_params!$C$2-scaling_params!$B$2)))+MAX(0,MIN(1,(L10-scaling_params!$B$3)/(scaling_params!$C$3-scaling_params!$B$3))))/2 -> 0.80686275 | Y10: =(MAX(0,MIN(1,(M10-scaling_params!$B$4)/(scaling_params!$C$4-scaling_params!$B$4)))+MAX(0,MIN(1,(N10-scaling_params!$B$5)/(scaling_params!$C$5-scaling_params!$B$5))))/2 -> 0.77559524 | Z10: =(MAX(0,MIN(1,(O10-scaling_params!$B$6)/(scaling_params!$C$6-scaling_params!$B$6)))+MAX(0,MIN(1,1-(P10-scaling_params!$B$7)/(scaling_params!$C$7-scaling_params!$B$7)))+MAX(0,MIN(1,(T10-scaling_params!$B$11)/(scaling_params!$C$11-scaling_params!$B$11))))/3 -> 0.93487773 | AA10: =(MAX(0,MIN(1,1-(Q10-scaling_params!$B$8)/(scaling_params!$C$8-scaling_params!$B$8)))+MAX(0,MIN(1,(R10-scaling_params!$B$9)/(scaling_params!$C$9-scaling_params!$B$9)))+MAX(0,MIN(1,(S10-scaling_params!$B$10)/(scaling_params!$C$10-scaling_params!$B$10))))/3 -> 0.93683296 | AB10: =(MAX(0,MIN(1,(U10-scaling_params!$B$12)/(scaling_params!$C$12-scaling_params!$B$12)))+MAX(0,MIN(1,(V10-scaling_params!$B$13)/(scaling_params!$C$13-scaling_params!$B$13))))/2 -> 0.73090909 | AC10: =(scaling_params!$G$2*X10+scaling_params!$G$3*Y10+scaling_params!$G$4*Z10+scaling_params!$G$5*AA10+scaling_params!$G$6*AB10)*100 -> 84.270377 | AD10: A-Strong | AE10: =IF(OR(AD10="B-Average",AD10="Benchmark"),1,0) -> 0
A11: 08c01be8 | B11: BBVA | C11: Andalucia | D11: Operations | E11: 2025 | F11: F | G11: 0-2 | H11: 1 | I11: 15.2 | J11: 0 | K11: 0 | L11: 7.8 | M11: 47 | N11: 0.89 | O11: 83.2 | P11: 5 | Q11: 10.1 | R11: 16.7 | S11: 4.6 | T11: 4 | U11: 3.6 | V11: 97 | W11: =AD11&"|"&B11&"|"&D11&"|"&E11 -> A-Strong|BBVA|Operations|2025 | X11: =(MAX(0,MIN(1,1-(K11-scaling_params!$B$2)/(scaling_params!$C$2-scaling_params!$B$2)))+MAX(0,MIN(1,(L11-scaling_params!$B$3)/(scaling_params!$C$3-scaling_params!$B$3))))/2 -> 0.85294118 | Y11: =(MAX(0,MIN(1,(M11-scaling_params!$B$4)/(scaling_params!$C$4-scaling_params!$B$4)))+MAX(0,MIN(1,(N11-scaling_params!$B$5)/(scaling_params!$C$5-scaling_params!$B$5))))/2 -> 0.84761905 | Z11: =(MAX(0,MIN(1,(O11-scaling_params!$B$6)/(scaling_params!$C$6-scaling_params!$B$6)))+MAX(0,MIN(1,1-(P11-scaling_params!$B$7)/(scaling_params!$C$7-scaling_params!$B$7)))+MAX(0,MIN(1,(T11-scaling_params!$B$11)/(scaling_params!$C$11-scaling_params!$B$11))))/3 -> 0.9047619 | AA11: =(MAX(0,MIN(1,1-(Q11-scaling_params!$B$8)/(scaling_params!$C$8-scaling_params!$B$8)))+MAX(0,MIN(1,(R11-scaling_params!$B$9)/(scaling_params!$C$9-scaling_params!$B$9)))+MAX(0,MIN(1,(S11-scaling_params!$B$10)/(scaling_params!$C$10-scaling_params!$B$10))))/3 -> 0.89327377 | AB11: =(MAX(0,MIN(1,(U11-scaling_params!$B$12)/(scaling_params!$C$12-scaling_params!$B$12)))+MAX(0,MIN(1,(V11-scaling_params!$B$13)/(scaling_params!$C$13-scaling_params!$B$13))))/2 -> 0.98727273 | AC11: =(scaling_params!$G$2*X11+scaling_params!$G$3*Y11+scaling_params!$G$4*Z11+scaling_params!$G$5*AA11+scaling_params!$G$6*AB11)*100 -> 88.596506 | AD11: A-Strong | AE11: =IF(OR(AD11="B-Average",AD11="Benchmark"),1,0) -> 0
A12: 08dd68d4 | B12: BBVA | C12: Andalucia | D12: Operations | E12: 2024 | F12: F | G12: 10+ | H12: 5 | I12: 15.8 | J12: 0 | K12: 1.1 | L12: 7.4 | M12: 11 | N12: 0.81 | O12: 77.5 | P12: 5.8 | Q12: 9.9 | R12: 17.5 | S12: 3.6 | T12: 3.3 | U12: 2.8 | V12: 88.2 | W12: =AD12&"|"&B12&"|"&D12&"|"&E12 -> A-Strong|BBVA|Operations|2024 | X12: =(MAX(0,MIN(1,1-(K12-scaling_params!$B$2)/(scaling_params!$C$2-scaling_params!$B$2)))+MAX(0,MIN(1,(L12-scaling_params!$B$3)/(scaling_params!$C$3-scaling_params!$B$3))))/2 -> 0.80686275 | Y12: =(MAX(0,MIN(1,(M12-scaling_params!$B$4)/(scaling_params!$C$4-scaling_params!$B$4)))+MAX(0,MIN(1,(N12-scaling_params!$B$5)/(scaling_params!$C$5-scaling_params!$B$5))))/2 -> 0.57619048 | Z12: =(MAX(0,MIN(1,(O12-scaling_params!$B$6)/(scaling_params!$C$6-scaling_params!$B$6)))+MAX(0,MIN(1,1-(P12-scaling_params!$B$7)/(scaling_params!$C$7-scaling_params!$B$7)))+MAX(0,MIN(1,(T12-scaling_params!$B$11)/(scaling_params!$C$11-scaling_params!$B$11))))/3 -> 0.81106821 | AA12: =(MAX(0,MIN(1,1-(Q12-scaling_params!$B$8)/(scaling_params!$C$8-scaling_params!$B$8)))+MAX(0,MIN(1,(R12-scaling_params!$B$9)/(scaling_params!$C$9-scaling_params!$B$9)))+MAX(0,MIN(1,(S12-scaling_params!$B$10)/(scaling_params!$C$10-scaling_params!$B$10))))/3 -> 0.82898982 | AB12: =(MAX(0,MIN(1,(U12-scaling_params!$B$12)/(scaling_params!$C$12-scaling_params!$B$12)))+MAX(0,MIN(1,(V12-scaling_params!$B$13)/(scaling_params!$C$13-scaling_params!$B$13))))/2 -> 0.85727273 | AC12: =(scaling_params!$G$2*X12+scaling_params!$G$3*Y12+scaling_params!$G$4*Z12+scaling_params!$G$5*AA12+scaling_params!$G$6*AB12)*100 -> 76.267893 | AD12: A-Strong | AE12: =IF(OR(AD12="B-Average",AD12="Benchmark"),1,0) -> 0
A13: 08dd68d4 | B13: BBVA | C13: Andalucia | D13: Operations | E13: 2025 | F13: F | G13: 10+ | H13: 5 | I13: 15.2 | J13: 0 | K13: 0 | L13: 6.9 | M13: 13 | N13: 0.76 | O13: 83.2 | P13: 5 | Q13: 10.1 | R13: 16.7 | S13: 3.7 | T13: 3.7 | U13: 3.6 | V13: 72.7 | W13: =AD13&"|"&B13&"|"&D13&"|"&E13 -> A-Strong|BBVA|Operations|2025 | X13: =(MAX(0,MIN(1,1-(K13-scaling_params!$B$2)/(scaling_params!$C$2-scaling_params!$B$2)))+MAX(0,MIN(1,(L13-scaling_params!$B$3)/(scaling_params!$C$3-scaling_params!$B$3))))/2 -> 0.78676471 | Y13: =(MAX(0,MIN(1,(M13-scaling_params!$B$4)/(scaling_params!$C$4-scaling_params!$B$4)))+MAX(0,MIN(1,(N13-scaling_params!$B$5)/(scaling_params!$C$5-scaling_params!$B$5))))/2 -> 0.52321429 | Z13: =(MAX(0,MIN(1,(O13-scaling_params!$B$6)/(scaling_params!$C$6-scaling_params!$B$6)))+MAX(0,MIN(1,1-(P13-scaling_params!$B$7)/(scaling_params!$C$7-scaling_params!$B$7)))+MAX(0,MIN(1,(T13-scaling_params!$B$11)/(scaling_params!$C$11-scaling_params!$B$11))))/3 -> 0.87619048 | AA13: =(MAX(0,MIN(1,1-(Q13-scaling_params!$B$8)/(scaling_params!$C$8-scaling_params!$B$8)))+MAX(0,MIN(1,(R13-scaling_params!$B$9)/(scaling_params!$C$9-scaling_params!$B$9)))+MAX(0,MIN(1,(S13-scaling_params!$B$10)/(scaling_params!$C$10-scaling_params!$B$10))))/3 -> 0.80503847 | AB13: =(MAX(0,MIN(1,(U13-scaling_params!$B$12)/(scaling_params!$C$12-scaling_params!$B$12)))+MAX(0,MIN(1,(V13-scaling_params!$B$13)/(scaling_params!$C$13-scaling_params!$B$13))))/2 -> 0.76636364 | AC13: =(scaling_params!$G$2*X13+scaling_params!$G$3*Y13+scaling_params!$G$4*Z13+scaling_params!$G$5*AA13+scaling_params!$G$6*AB13)*100 -> 74.58675 | AD13: A-Strong | AE13: =IF(OR(AD13="B-Average",AD13="Benchmark"),1,0) -> 0
... A3801: d9862e28 | B3801: Santander | C3801: Pais Vasco | D3801: Digital | E3801: 2025 | F3801: F | G3801: 3-5 | H3801: 3 | I3801: 7.1 | J3801: 0 | K3801: 1.6 | L3801: 7.4 | M3801: 10 | N3801: 0.84 | O3801: 68 | P3801: 6.4 | Q3801: 16 | R3801: 14.4 | S3801: 3.4 | T3801: 3.4 | U3801: 1.8 | V3801: 64.3 | W3801: =AD3801&"|"&B3801&"|"&D3801&"|"&E3801 -> Benchmark|Santander|Digital|2025 | X3801: =(MAX(0,MIN(1,1-(K3801-scaling_params!$B$2)/(scaling_params!$C$2-scaling_params!$B$2)))+MAX(0,MIN(1,(L3801-scaling_params!$B$3)/(scaling_params!$C$3-scaling_params!$B$3))))/2 -> 0.72352941 | Y3801: =(MAX(0,MIN(1,(M3801-scaling_params!$B$4)/(scaling_params!$C$4-scaling_params!$B$4)))+MAX(0,MIN(1,(N3801-scaling_params!$B$5)/(scaling_params!$C$5-scaling_params!$B$5))))/2 -> 0.60892857 | Z3801: =(MAX(0,MIN(1,(O3801-scaling_params!$B$6)/(scaling_params!$C$6-scaling_params!$B$6)))+MAX(0,MIN(1,1-(P3801-scaling_params!$B$7)/(scaling_params!$C$7-scaling_params!$B$7)))+MAX(0,MIN(1,(T3801-scaling_params!$B$11)/(scaling_params!$C$11-scaling_params!$B$11))))/3 -> 0.62132345 | AA3801: =(MAX(0,MIN(1,1-(Q3801-scaling_params!$B$8)/(scaling_params!$C$8-scaling_params!$B$8)))+MAX(0,MIN(1,(R3801-scaling_params!$B$9)/(scaling_params!$C$9-scaling_params!$B$9)))+MAX(0,MIN(1,(S3801-scaling_params!$B$10)/(scaling_params!$C$10-scaling_params!$B$10))))/3 -> 0.51191363 | AB3801: =(MAX(0,MIN(1,(U3801-scaling_params!$B$12)/(scaling_params!$C$12-scaling_params!$B$12)))+MAX(0,MIN(1,(V3801-scaling_params!$B$13)/(scaling_params!$C$13-scaling_params!$B$13))))/2 -> 0.39 | AC3801: =(scaling_params!$G$2*X3801+scaling_params!$G$3*Y3801+scaling_params!$G$4*Z3801+scaling_params!$G$5*AA3801+scaling_params!$G$6*AB3801)*100 -> 59.525543 | AD3801: Benchmark | AE3801: =IF(OR(AD3801="B-Average",AD3801="Benchmark"),1,0) -> 1

Sheet scaling_params
A1: Indicator | B1: Worst value in peer group (Min) | C1: Best value in peer group (Max) | D1: Good direction | F1: How much each dimension counts (weight) | G1: Value
A2: comply_inc | B2: =MINIFS(employee_year!K$2:K$3801,employee_year!$AE$2:$AE$3801,1) -> 1 | C2: =MAXIFS(employee_year!K$2:K$3801,employee_year!$AE$2:$AE$3801,1) -> 4 | D2: − | F2: Ethics (w1) | G2: 0.235
A3: ethics_sc | B3: =MINIFS(employee_year!L$2:L$3801,employee_year!$AE$2:$AE$3801,1) -> 3 | C3: =MAXIFS(employee_year!L$2:L$3801,employee_year!$AE$2:$AE$3801,1) -> 9.8 | D3: + | F3: Satisfaction (w2) | G3: 0.235
A4: enps | B4: =MINIFS(employee_year!M$2:M$3801,employee_year!$AE$2:$AE$3801,1) -> -47 | C4: =MAXIFS(employee_year!M$2:M$3801,employee_year!$AE$2:$AE$3801,1) -> 58 | D4: + | F4: Engagement (w3) | G4: 0.235
A5: pay_equity | B5: =MINIFS(employee_year!N$2:N$3801,employee_year!$AE$2:$AE$3801,1) -> 0.57 | C5: =MAXIFS(employee_year!N$2:N$3801,employee_year!$AE$2:$AE$3801,1) -> 0.97 | D5: + | F5: Employee Experience (w4) | G5: 0.176
A6: particip_rate | B6: =MINIFS(employee_year!O$2:O$3801,employee_year!$AE$2:$AE$3801,1) -> 56.6 | C6: =MAXIFS(employee_year!O$2:O$3801,employee_year!$AE$2:$AE$3801,1) -> 76.8 | D6: + | F6: Innovation (w5) | G6: 0.118
A7: absent_rate | B7: =MINIFS(employee_year!P$2:P$3801,employee_year!$AE$2:$AE$3801,1) -> 5.5 | C7: =MAXIFS(employee_year!P$2:P$3801,employee_year!$AE$2:$AE$3801,1) -> 9.2 | D7: − | F7: Sum (must equal 1) | G7: =SUM(G2:G6) -> 0.999
A8: turnover_rate | B8: =MINIFS(employee_year!Q$2:Q$3801,employee_year!$AE$2:$AE$3801,1) -> 11.6 | C8: =MAXIFS(employee_year!Q$2:Q$3801,employee_year!$AE$2:$AE$3801,1) -> 20.4 | D8: −
A9: mob_rate | B9: =MINIFS(employee_year!R$2:R$3801,employee_year!$AE$2:$AE$3801,1) -> 10.4 | C9: =MAXIFS(employee_year!R$2:R$3801,employee_year!$AE$2:$AE$3801,1) -> 18.3 | D9: + | F9: How rescaling works: for each indicator, the worst value in the base case (Average scenario + peer banks) becomes 0 and the best becomes 1. Indicators where lower is better (e.g. turnover) are flipped first. The Strong and Weak test copies are scored against these same goalposts.
A10: trust_360 | B10: =MINIFS(employee_year!S$2:S$3801,employee_year!$AE$2:$AE$3801,1) -> 1.6 | C10: =MAXIFS(employee_year!S$2:S$3801,employee_year!$AE$2:$AE$3801,1) -> 5 | D10: +
A11: psych_safety | B11: =MINIFS(employee_year!T$2:T$3801,employee_year!$AE$2:$AE$3801,1) -> 1.5 | C11: =MAXIFS(employee_year!T$2:T$3801,employee_year!$AE$2:$AE$3801,1) -> 5 | D11: +
A12: ideas_100fte | B12: =MINIFS(employee_year!U$2:U$3801,employee_year!$AE$2:$AE$3801,1) -> 1 | C12: =MAXIFS(employee_year!U$2:U$3801,employee_year!$AE$2:$AE$3801,1) -> 3 | D12: +
A13: training_compl | B13: =MINIFS(employee_year!V$2:V$3801,employee_year!$AE$2:$AE$3801,1) -> 43.4 | C13: =MAXIFS(employee_year!V$2:V$3801,employee_year!$AE$2:$AE$3801,1) -> 98.4 | D13: +

Sheet dept_year
A1: scenario | B1: bank | C1: dept | D1: year | E1: key | F1: n_emp | G1: avg_enps | H1: turnover_rate | I1: absent_rate | J1: particip_rate | K1: comply_inc | L1: ideas_100fte | M1: mob_rate | N1: exit_rate | O1: avg_culture_idx
A2: B-Average | B2: BBVA | C2: Corporate | D2: 2024 | E2: =A2&"|"&B2&"|"&C2&"|"&D2 -> B-Average|BBVA|Corporate|2024 | F2: =COUNTIF(employee_year!$W$2:$W$3801,E2) -> 96 | G2: =AVERAGEIF(employee_year!$W$2:$W$3801,E2,employee_year!M$2:M$3801) -> 13.041667 | H2: =AVERAGEIF(employee_year!$W$2:$W$3801,E2,employee_year!Q$2:Q$3801) -> 14.6 | I2: =AVERAGEIF(employee_year!$W$2:$W$3801,E2,employee_year!P$2:P$3801) -> 8.4 | J2: =AVERAGEIF(employee_year!$W$2:$W$3801,E2,employee_year!O$2:O$3801) -> 71.5 | K2: =AVERAGEIF(employee_year!$W$2:$W$3801,E2,employee_year!K$2:K$3801) -> 3.1 | L2: =AVERAGEIF(employee_year!$W$2:$W$3801,E2,employee_year!U$2:U$3801) -> 1.8 | M2: =AVERAGEIF(employee_year!$W$2:$W$3801,E2,employee_year!R$2:R$3801) -> 11.7 | N2: =AVERAGEIF(employee_year!$W$2:$W$3801,E2,employee_year!J$2:J$3801) -> 0.125 | O2: =AVERAGEIF(employee_year!$W$2:$W$3801,E2,employee_year!AC$2:AC$3801) -> 47.482558
A3: B-Average | B3: BBVA | C3: Corporate | D3: 2025 | E3: =A3&"|"&B3&"|"&C3&"|"&D3 -> B-Average|BBVA|Corporate|2025 | F3: =COUNTIF(employee_year!$W$2:$W$3801,E3) -> 96 | G3: =AVERAGEIF(employee_year!$W$2:$W$3801,E3,employee_year!M$2:M$3801) -> 10.927083 | H3: =AVERAGEIF(employee_year!$W$2:$W$3801,E3,employee_year!Q$2:Q$3801) -> 14.3 | I3: =AVERAGEIF(employee_year!$W$2:$W$3801,E3,employee_year!P$2:P$3801) -> 8 | J3: =AVERAGEIF(employee_year!$W$2:$W$3801,E3,employee_year!O$2:O$3801) -> 66 | K3: =AVERAGEIF(employee_year!$W$2:$W$3801,E3,employee_year!K$2:K$3801) -> 2 | L3: =AVERAGEIF(employee_year!$W$2:$W$3801,E3,employee_year!U$2:U$3801) -> 1.4 | M3: =AVERAGEIF(employee_year!$W$2:$W$3801,E3,employee_year!R$2:R$3801) -> 13.5 | N3: =AVERAGEIF(employee_year!$W$2:$W$3801,E3,employee_year!J$2:J$3801) -> 0.11458333 | O3: =AVERAGEIF(employee_year!$W$2:$W$3801,E3,employee_year!AC$2:AC$3801) -> 51.779852
A4: B-Average | B4: BBVA | C4: Digital | D4: 2024 | E4: =A4&"|"&B4&"|"&C4&"|"&D4 -> B-Average|BBVA|Digital|2024 | F4: =COUNTIF(employee_year!$W$2:$W$3801,E4) -> 106 | G4: =AVERAGEIF(employee_year!$W$2:$W$3801,E4,employee_year!M$2:M$3801) -> 1.8018868 | H4: =AVERAGEIF(employee_year!$W$2:$W$3801,E4,employee_year!Q$2:Q$3801) -> 18.1 | I4: =AVERAGEIF(employee_year!$W$2:$W$3801,E4,employee_year!P$2:P$3801) -> 8.7 | J4: =AVERAGEIF(employee_year!$W$2:$W$3801,E4,employee_year!O$2:O$3801) -> 61.5 | K4: =AVERAGEIF(employee_year!$W$2:$W$3801,E4,employee_year!K$2:K$3801) -> 3 | L4: =AVERAGEIF(employee_year!$W$2:$W$3801,E4,employee_year!U$2:U$3801) -> 1.3 | M4: =AVERAGEIF(employee_year!$W$2:$W$3801,E4,employee_year!R$2:R$3801) -> 13 | N4: =AVERAGEIF(employee_year!$W$2:$W$3801,E4,employee_year!J$2:J$3801) -> 0.18867925 | O4: =AVERAGEIF(employee_year!$W$2:$W$3801,E4,employee_year!AC$2:AC$3801) -> 36.433735
A5: B-Average | B5: BBVA | C5: Digital | D5: 2025 | E5: =A5&"|"&B5&"|"&C5&"|"&D5 -> B-Average|BBVA|Digital|2025 | F5: =COUNTIF(employee_year!$W$2:$W$3801,E5) -> 106 | G5: =AVERAGEIF(employee_year!$W$2:$W$3801,E5,employee_year!M$2:M$3801) -> 6.5188679 | H5: =AVERAGEIF(employee_year!$W$2:$W$3801,E5,employee_year!Q$2:Q$3801) -> 16.6 | I5: =AVERAGEIF(employee_year!$W$2:$W$3801,E5,employee_year!P$2:P$3801) -> 7.6 | J5: =AVERAGEIF(employee_year!$W$2:$W$3801,E5,employee_year!O$2:O$3801) -> 62.8 | K5: =AVERAGEIF(employee_year!$W$2:$W$3801,E5,employee_year!K$2:K$3801) -> 3.2 | L5: =AVERAGEIF(employee_year!$W$2:$W$3801,E5,employee_year!U$2:U$3801) -> 1.7 | M5: =AVERAGEIF(employee_year!$W$2:$W$3801,E5,employee_year!R$2:R$3801) -> 15.2 | N5: =AVERAGEIF(employee_year!$W$2:$W$3801,E5,employee_year!J$2:J$3801) -> 0.16037736 | O5: =AVERAGEIF(employee_year!$W$2:$W$3801,E5,employee_year!AC$2:AC$3801) -> 43.592852
A6: B-Average | B6: BBVA | C6: Operations | D6: 2024 | E6: =A6&"|"&B6&"|"&C6&"|"&D6 -> B-Average|BBVA|Operations|2024 | F6: =COUNTIF(employee_year!$W$2:$W$3801,E6) -> 109 | G6: =AVERAGEIF(employee_year!$W$2:$W$3801,E6,employee_year!M$2:M$3801) -> 7.2110092 | H6: =AVERAGEIF(employee_year!$W$2:$W$3801,E6,employee_year!Q$2:Q$3801) -> 16.3 | I6: =AVERAGEIF(employee_year!$W$2:$W$3801,E6,employee_year!P$2:P$3801) -> 7 | J6: =AVERAGEIF(employee_year!$W$2:$W$3801,E6,employee_year!O$2:O$3801) -> 69.1 | K6: =AVERAGEIF(employee_year!$W$2:$W$3801,E6,employee_year!K$2:K$3801) -> 3 | L6: =AVERAGEIF(employee_year!$W$2:$W$3801,E6,employee_year!U$2:U$3801) -> 2.1 | M6: =AVERAGEIF(employee_year!$W$2:$W$3801,E6,employee_year!R$2:R$3801) -> 13.4 | N6: =AVERAGEIF(employee_year!$W$2:$W$3801,E6,employee_year!J$2:J$3801) -> 0.12844037 | O6: =AVERAGEIF(employee_year!$W$2:$W$3801,E6,employee_year!AC$2:AC$3801) -> 49.427574
A7: B-Average | B7: BBVA | C7: Operations | D7: 2025 | E7: =A7&"|"&B7&"|"&C7&"|"&D7 -> B-Average|BBVA|Operations|2025 | F7: =COUNTIF(employee_year!$W$2:$W$3801,E7) -> 109 | G7: =AVERAGEIF(employee_year!$W$2:$W$3801,E7,employee_year!M$2:M$3801) -> 8.0642202 | H7: =AVERAGEIF(employee_year!$W$2:$W$3801,E7,employee_year!Q$2:Q$3801) -> 15.9 | I7: =AVERAGEIF(employee_year!$W$2:$W$3801,E7,employee_year!P$2:P$3801) -> 7.5 | J7: =AVERAGEIF(employee_year!$W$2:$W$3801,E7,employee_year!O$2:O$3801) -> 65 | K7: =AVERAGEIF(employee_year!$W$2:$W$3801,E7,employee_year!K$2:K$3801) -> 2.9 | L7: =AVERAGEIF(employee_year!$W$2:$W$3801,E7,employee_year!U$2:U$3801) -> 1.3 | M7: =AVERAGEIF(employee_year!$W$2:$W$3801,E7,employee_year!R$2:R$3801) -> 10.7 | N7: =AVERAGEIF(employee_year!$W$2:$W$3801,E7,employee_year!J$2:J$3801) -> 0.12844037 | O7: =AVERAGEIF(employee_year!$W$2:$W$3801,E7,employee_year!AC$2:AC$3801) -> 43.777866
A8: B-Average | B8: BBVA | C8: Retail | D8: 2024 | E8: =A8&"|"&B8&"|"&C8&"|"&D8 -> B-Average|BBVA|Retail|2024 | F8: =COUNTIF(employee_year!$W$2:$W$3801,E8) -> 82 | G8: =AVERAGEIF(employee_year!$W$2:$W$3801,E8,employee_year!M$2:M$3801) -> 8.4512195 | H8: =AVERAGEIF(employee_year!$W$2:$W$3801,E8,employee_year!Q$2:Q$3801) -> 16.4 | I8: =AVERAGEIF(employee_year!$W$2:$W$3801,E8,employee_year!P$2:P$3801) -> 8.1 | J8: =AVERAGEIF(employee_year!$W$2:$W$3801,E8,employee_year!O$2:O$3801) -> 68.1 | K8: =AVERAGEIF(employee_year!$W$2:$W$3801,E8,employee_year!K$2:K$3801) -> 2.9 | L8: =AVERAGEIF(employee_year!$W$2:$W$3801,E8,employee_year!U$2:U$3801) -> 2.1 | M8: =AVERAGEIF(employee_year!$W$2:$W$3801,E8,employee_year!R$2:R$3801) -> 13.3 | N8: =AVERAGEIF(employee_year!$W$2:$W$3801,E8,employee_year!J$2:J$3801) -> 0.13414634 | O8: =AVERAGEIF(employee_year!$W$2:$W$3801,E8,employee_year!AC$2:AC$3801) -> 47.457639
A9: B-Average | B9: BBVA | C9: Retail | D9: 2025 | E9: =A9&"|"&B9&"|"&C9&"|"&D9 -> B-Average|BBVA|Retail|2025 | F9: =COUNTIF(employee_year!$W$2:$W$3801,E9) -> 82 | G9: =AVERAGEIF(employee_year!$W$2:$W$3801,E9,employee_year!M$2:M$3801) -> 8.695122 | H9: =AVERAGEIF(employee_year!$W$2:$W$3801,E9,employee_year!Q$2:Q$3801) -> 20.4 | I9: =AVERAGEIF(employee_year!$W$2:$W$3801,E9,employee_year!P$2:P$3801) -> 6.2 | J9: =AVERAGEIF(employee_year!$W$2:$W$3801,E9,employee_year!O$2:O$3801) -> 69.9 | K9: =AVERAGEIF(employee_year!$W$2:$W$3801,E9,employee_year!K$2:K$3801) -> 2.8 | L9: =AVERAGEIF(employee_year!$W$2:$W$3801,E9,employee_year!U$2:U$3801) -> 1.6 | M9: =AVERAGEIF(employee_year!$W$2:$W$3801,E9,employee_year!R$2:R$3801) -> 11.3 | N9: =AVERAGEIF(employee_year!$W$2:$W$3801,E9,employee_year!J$2:J$3801) -> 0.097560976 | O9: =AVERAGEIF(employee_year!$W$2:$W$3801,E9,employee_year!AC$2:AC$3801) -> 47.847355
A10: B-Average | B10: BBVA | C10: Risk | D10: 2024 | E10: =A10&"|"&B10&"|"&C10&"|"&D10 -> B-Average|BBVA|Risk|2024 | F10: =COUNTIF(employee_year!$W$2:$W$3801,E10) -> 107 | G10: =AVERAGEIF(employee_year!$W$2:$W$3801,E10,employee_year!M$2:M$3801) -> 13.71028 | H10: =AVERAGEIF(employee_year!$W$2:$W$3801,E10,employee_year!Q$2:Q$3801) -> 13.6 | I10: =AVERAGEIF(employee_year!$W$2:$W$3801,E10,employee_year!P$2:P$3801) -> 8.3 | J10: =AVERAGEIF(employee_year!$W$2:$W$3801,E10,employee_year!O$2:O$3801) -> 70.5 | K10: =AVERAGEIF(employee_year!$W$2:$W$3801,E10,employee_year!K$2:K$3801) -> 2.4 | L10: =AVERAGEIF(employee_year!$W$2:$W$3801,E10,employee_year!U$2:U$3801) -> 1.7 | M10: =AVERAGEIF(employee_year!$W$2:$W$3801,E10,employee_year!R$2:R$3801) -> 14.9 | N10: =AVERAGEIF(employee_year!$W$2:$W$3801,E10,employee_year!J$2:J$3801) -> 0.1588785 | O10: =AVERAGEIF(employee_year!$W$2:$W$3801,E10,employee_year!AC$2:AC$3801) -> 55.652409
A11: B-Average | B11: BBVA | C11: Risk | D11: 2025 | E11: =A11&"|"&B11&"|"&C11&"|"&D11 -> B-Average|BBVA|Risk|2025 | F11: =COUNTIF(employee_year!$W$2:$W$3801,E11) -> 107 | G11: =AVERAGEIF(employee_year!$W$2:$W$3801,E11,employee_year!M$2:M$3801) -> 17.420561 | H11: =AVERAGEIF(employee_year!$W$2:$W$3801,E11,employee_year!Q$2:Q$3801) -> 16.6 | I11: =AVERAGEIF(employee_year!$W$2:$W$3801,E11,employee_year!P$2:P$3801) -> 7 | J11: =AVERAGEIF(employee_year!$W$2:$W$3801,E11,employee_year!O$2:O$3801) -> 68.8 | K11: =AVERAGEIF(employee_year!$W$2:$W$3801,E11,employee_year!K$2:K$3801) -> 2.5 | L11: =AVERAGEIF(employee_year!$W$2:$W$3801,E11,employee_year!U$2:U$3801) -> 1.5 | M11: =AVERAGEIF(employee_year!$W$2:$W$3801,E11,employee_year!R$2:R$3801) -> 14.7 | N11: =AVERAGEIF(employee_year!$W$2:$W$3801,E11,employee_year!J$2:J$3801) -> 0.12149533 | O11: =AVERAGEIF(employee_year!$W$2:$W$3801,E11,employee_year!AC$2:AC$3801) -> 56.087228
A12: Benchmark | B12: Bankinter | C12: Corporate | D12: 2024 | E12: =A12&"|"&B12&"|"&C12&"|"&D12 -> Benchmark|Bankinter|Corporate|2024 | F12: =COUNTIF(employee_year!$W$2:$W$3801,E12) -> 22 | G12: =AVERAGEIF(employee_year!$W$2:$W$3801,E12,employee_year!M$2:M$3801) -> 11.272727 | H12: =AVERAGEIF(employee_year!$W$2:$W$3801,E12,employee_year!Q$2:Q$3801) -> 16.5 | I12: =AVERAGEIF(employee_year!$W$2:$W$3801,E12,employee_year!P$2:P$3801) -> 5.9 | J12: =AVERAGEIF(employee_year!$W$2:$W$3801,E12,employee_year!O$2:O$3801) -> 71.1 | K12: =AVERAGEIF(employee_year!$W$2:$W$3801,E12,employee_year!K$2:K$3801) -> 1.7 | L12: =AVERAGEIF(employee_year!$W$2:$W$3801,E12,employee_year!U$2:U$3801) -> 1.5 | M12: =AVERAGEIF(employee_year!$W$2:$W$3801,E12,employee_year!R$2:R$3801) -> 13.8 | N12: =AVERAGEIF(employee_year!$W$2:$W$3801,E12,employee_year!J$2:J$3801) -> 0.090909091 | O12: =AVERAGEIF(employee_year!$W$2:$W$3801,E12,employee_year!AC$2:AC$3801) -> 59.204549
A13: Benchmark | B13: Bankinter | C13: Corporate | D13: 2025 | E13: =A13&"|"&B13&"|"&C13&"|"&D13 -> Benchmark|Bankinter|Corporate|2025 | F13: =COUNTIF(employee_year!$W$2:$W$3801,E13) -> 22 | G13: =AVERAGEIF(employee_year!$W$2:$W$3801,E13,employee_year!M$2:M$3801) -> 13.818182 | H13: =AVERAGEIF(employee_year!$W$2:$W$3801,E13,employee_year!Q$2:Q$3801) -> 14.9 | I13: =AVERAGEIF(employee_year!$W$2:$W$3801,E13,employee_year!P$2:P$3801) -> 5.6 | J13: =AVERAGEIF(employee_year!$W$2:$W$3801,E13,employee_year!O$2:O$3801) -> 73.8 | K13: =AVERAGEIF(employee_year!$W$2:$W$3801,E13,employee_year!K$2:K$3801) -> 1.4 | L13: =AVERAGEIF(employee_year!$W$2:$W$3801,E13,employee_year!U$2:U$3801) -> 2 | M13: =AVERAGEIF(employee_year!$W$2:$W$3801,E13,employee_year!R$2:R$3801) -> 13.8 | N13: =AVERAGEIF(employee_year!$W$2:$W$3801,E13,employee_year!J$2:J$3801) -> 0.13636364 | O13: =AVERAGEIF(employee_year!$W$2:$W$3801,E13,employee_year!AC$2:AC$3801) -> 66.007341
... A51: Benchmark | B51: Santander | C51: Risk | D51: 2025 | E51: =A51&"|"&B51&"|"&C51&"|"&D51 -> Benchmark|Santander|Risk|2025 | F51: =COUNTIF(employee_year!$W$2:$W$3801,E51) -> 26 | G51: =AVERAGEIF(employee_year!$W$2:$W$3801,E51,employee_year!M$2:M$3801) -> 21.769231 | H51: =AVERAGEIF(employee_year!$W$2:$W$3801,E51,employee_year!Q$2:Q$3801) -> 15.4 | I51: =AVERAGEIF(employee_year!$W$2:$W$3801,E51,employee_year!P$2:P$3801) -> 7 | J51: =AVERAGEIF(employee_year!$W$2:$W$3801,E51,employee_year!O$2:O$3801) -> 73.6 | K51: =AVERAGEIF(employee_year!$W$2:$W$3801,E51,employee_year!K$2:K$3801) -> 1.4 | L51: =AVERAGEIF(employee_year!$W$2:$W$3801,E51,employee_year!U$2:U$3801) -> 2.4 | M51: =AVERAGEIF(employee_year!$W$2:$W$3801,E51,employee_year!R$2:R$3801) -> 16.6 | N51: =AVERAGEIF(employee_year!$W$2:$W$3801,E51,employee_year!J$2:J$3801) -> 0.076923077 | O51: =AVERAGEIF(employee_year!$W$2:$W$3801,E51,employee_year!AC$2:AC$3801) -> 69.152201

Sheet bank_year
A1: bank | B1: year | C1: scenario used | D1: n_obs | E1: culture_idx (from employee data) | F1: brand_trust (0-10) | G1: cust_nps | H1: cust_attrition (%) | I1: glassdoor_rating (1-5) | J1: roa (%) | K1: revenue_growth (%) | L1: mktcap_eur_m
A2: BBVA | B2: 2024 | C2: B-Average | D2: =COUNTIFS(employee_year!$B$2:$B$3801,A2,employee_year!$E$2:$E$3801,B2,employee_year!$AD$2:$AD$3801,C2) -> 500 | E2: =AVERAGEIFS(employee_year!$AC$2:$AC$3801,employee_year!$B$2:$B$3801,A2,employee_year!$E$2:$E$3801,B2,employee_year!$AD$2:$AD$3801,C2) -> 47.308482 | F2: 5.9 | G2: 24 | H2: 11.5 | I2: 3.9
A3: BBVA | B3: 2025 | C3: B-Average | D3: =COUNTIFS(employee_year!$B$2:$B$3801,A3,employee_year!$E$2:$E$3801,B3,employee_year!$AD$2:$AD$3801,C3) -> 500 | E3: =AVERAGEIFS(employee_year!$AC$2:$AC$3801,employee_year!$B$2:$B$3801,A3,employee_year!$E$2:$E$3801,B3,employee_year!$AD$2:$AD$3801,C3) -> 48.576624 | F3: 6 | G3: 27 | H3: 11 | I3: 4 | J3: 1.23 | K3: 8.2 | L3: 108872
A4: Santander | B4: 2024 | C4: Benchmark | D4: =COUNTIFS(employee_year!$B$2:$B$3801,A4,employee_year!$E$2:$E$3801,B4,employee_year!$AD$2:$AD$3801,C4) -> 100 | E4: =AVERAGEIFS(employee_year!$AC$2:$AC$3801,employee_year!$B$2:$B$3801,A4,employee_year!$E$2:$E$3801,B4,employee_year!$AD$2:$AD$3801,C4) -> 65.815449 | F4: 7 | G4: 35 | H4: 9.5 | I4: 3.8
A5: Santander | B5: 2025 | C5: Benchmark | D5: =COUNTIFS(employee_year!$B$2:$B$3801,A5,employee_year!$E$2:$E$3801,B5,employee_year!$AD$2:$AD$3801,C5) -> 100 | E5: =AVERAGEIFS(employee_year!$AC$2:$AC$3801,employee_year!$B$2:$B$3801,A5,employee_year!$E$2:$E$3801,B5,employee_year!$AD$2:$AD$3801,C5) -> 67.605801 | F5: 7.1 | G5: 36 | H5: 9.2 | I5: 3.9 | J5: 0.81 | K5: 7.5 | L5: 151213
A6: Sabadell | B6: 2024 | C6: Benchmark | D6: =COUNTIFS(employee_year!$B$2:$B$3801,A6,employee_year!$E$2:$E$3801,B6,employee_year!$AD$2:$AD$3801,C6) -> 100 | E6: =AVERAGEIFS(employee_year!$AC$2:$AC$3801,employee_year!$B$2:$B$3801,A6,employee_year!$E$2:$E$3801,B6,employee_year!$AD$2:$AD$3801,C6) -> 41.537995 | F6: 6.3 | G6: 26 | H6: 11 | I6: 3.5
A7: Sabadell | B7: 2025 | C7: Benchmark | D7: =COUNTIFS(employee_year!$B$2:$B$3801,A7,employee_year!$E$2:$E$3801,B7,employee_year!$AD$2:$AD$3801,C7) -> 100 | E7: =AVERAGEIFS(employee_year!$AC$2:$AC$3801,employee_year!$B$2:$B$3801,A7,employee_year!$E$2:$E$3801,B7,employee_year!$AD$2:$AD$3801,C7) -> 41.287725 | F7: 6.4 | G7: 27 | H7: 10.8 | I7: 3.6 | J7: 0.68 | K7: 5.5 | L7: 14144
A8: CaixaBank | B8: 2024 | C8: Benchmark | D8: =COUNTIFS(employee_year!$B$2:$B$3801,A8,employee_year!$E$2:$E$3801,B8,employee_year!$AD$2:$AD$3801,C8) -> 100 | E8: =AVERAGEIFS(employee_year!$AC$2:$AC$3801,employee_year!$B$2:$B$3801,A8,employee_year!$E$2:$E$3801,B8,employee_year!$AD$2:$AD$3801,C8) -> 50.195084 | F8: 6.6 | G8: 30 | H8: 10.2 | I8: 3.7
A9: CaixaBank | B9: 2025 | C9: Benchmark | D9: =COUNTIFS(employee_year!$B$2:$B$3801,A9,employee_year!$E$2:$E$3801,B9,employee_year!$AD$2:$AD$3801,C9) -> 100 | E9: =AVERAGEIFS(employee_year!$AC$2:$AC$3801,employee_year!$B$2:$B$3801,A9,employee_year!$E$2:$E$3801,B9,employee_year!$AD$2:$AD$3801,C9) -> 55.845709 | F9: 6.7 | G9: 31 | H9: 10 | I9: 3.8 | J9: 0.92 | K9: 6.4 | L9: 79287
A10: Bankinter | B10: 2024 | C10: Benchmark | D10: =COUNTIFS(employee_year!$B$2:$B$3801,A10,employee_year!$E$2:$E$3801,B10,employee_year!$AD$2:$AD$3801,C10) -> 100 | E10: =AVERAGEIFS(employee_year!$AC$2:$AC$3801,employee_year!$B$2:$B$3801,A10,employee_year!$E$2:$E$3801,B10,employee_year!$AD$2:$AD$3801,C10) -> 50.132484 | F10: 6.5 | G10: 28 | H10: 10.6 | I10: 3.6
A11: Bankinter | B11: 2025 | C11: Benchmark | D11: =COUNTIFS(employee_year!$B$2:$B$3801,A11,employee_year!$E$2:$E$3801,B11,employee_year!$AD$2:$AD$3801,C11) -> 100 | E11: =AVERAGEIFS(employee_year!$AC$2:$AC$3801,employee_year!$B$2:$B$3801,A11,employee_year!$E$2:$E$3801,B11,employee_year!$AD$2:$AD$3801,C11) -> 54.46473 | F11: 6.5 | G11: 29 | H11: 10.4 | I11: 3.7 | J11: 0.87 | K11: 6 | L11: 12483
A13: How to read this sheet: the BBVA index is the average of its B-Average (base case) rows. Brand trust, customer NPS, attrition and Glassdoor are customer/outside measures - we keep them OUT of the index on purpose, and use them only to check whether the index predicts them. Numbers are invented unless a cell has a red comment naming a real source.

Sheet scenario_summary
A1: The quality check: the same 500 invented BBVA employees, “surveyed” in three different worlds. Averages update live from the main table.
A3: Metric | B3: A-Strong | C3: B-Average | D3: C-Weak | E3: Benchmark (peers)
A4: Culture Index (0–100) | B4: =AVERAGEIFS(employee_year!AC$2:AC$3801,employee_year!$AD$2:$AD$3801,"A-Strong",employee_year!$B$2:$B$3801,"BBVA") -> 85.3819 | C4: =AVERAGEIFS(employee_year!AC$2:AC$3801,employee_year!$AD$2:$AD$3801,"B-Average",employee_year!$B$2:$B$3801,"BBVA") -> 47.942553 | D4: =AVERAGEIFS(employee_year!AC$2:AC$3801,employee_year!$AD$2:$AD$3801,"C-Weak",employee_year!$B$2:$B$3801,"BBVA") -> 13.404611 | E4: =AVERAGEIFS(employee_year!AC$2:AC$3801,employee_year!$AD$2:$AD$3801,"Benchmark",employee_year!$B$2:$B$3801,"<>BBVA") -> 53.360622
A5: eNPS | B5: =AVERAGEIFS(employee_year!M$2:M$3801,employee_year!$AD$2:$AD$3801,"A-Strong",employee_year!$B$2:$B$3801,"BBVA") -> 31.177 | C5: =AVERAGEIFS(employee_year!M$2:M$3801,employee_year!$AD$2:$AD$3801,"B-Average",employee_year!$B$2:$B$3801,"BBVA") -> 9.585 | D5: =AVERAGEIFS(employee_year!M$2:M$3801,employee_year!$AD$2:$AD$3801,"C-Weak",employee_year!$B$2:$B$3801,"BBVA") -> -16.79 | E5: =AVERAGEIFS(employee_year!M$2:M$3801,employee_year!$AD$2:$AD$3801,"Benchmark",employee_year!$B$2:$B$3801,"<>BBVA") -> 9.45625
A6: Exit rate | B6: =AVERAGEIFS(employee_year!J$2:J$3801,employee_year!$AD$2:$AD$3801,"A-Strong",employee_year!$B$2:$B$3801,"BBVA") -> 0.052 | C6: =AVERAGEIFS(employee_year!J$2:J$3801,employee_year!$AD$2:$AD$3801,"B-Average",employee_year!$B$2:$B$3801,"BBVA") -> 0.137 | D6: =AVERAGEIFS(employee_year!J$2:J$3801,employee_year!$AD$2:$AD$3801,"C-Weak",employee_year!$B$2:$B$3801,"BBVA") -> 0.204 | E6: =AVERAGEIFS(employee_year!J$2:J$3801,employee_year!$AD$2:$AD$3801,"Benchmark",employee_year!$B$2:$B$3801,"<>BBVA") -> 0.1075
A7: Turnover rate (%) | B7: =AVERAGEIFS(employee_year!Q$2:Q$3801,employee_year!$AD$2:$AD$3801,"A-Strong",employee_year!$B$2:$B$3801,"BBVA") -> 10.6006 | C7: =AVERAGEIFS(employee_year!Q$2:Q$3801,employee_year!$AD$2:$AD$3801,"B-Average",employee_year!$B$2:$B$3801,"BBVA") -> 16.2114 | D7: =AVERAGEIFS(employee_year!Q$2:Q$3801,employee_year!$AD$2:$AD$3801,"C-Weak",employee_year!$B$2:$B$3801,"BBVA") -> 22.8581 | E7: =AVERAGEIFS(employee_year!Q$2:Q$3801,employee_year!$AD$2:$AD$3801,"Benchmark",employee_year!$B$2:$B$3801,"<>BBVA") -> 15.427375
A8: Ideas per 100 FTE | B8: =AVERAGEIFS(employee_year!U$2:U$3801,employee_year!$AD$2:$AD$3801,"A-Strong",employee_year!$B$2:$B$3801,"BBVA") -> 3.4426 | C8: =AVERAGEIFS(employee_year!U$2:U$3801,employee_year!$AD$2:$AD$3801,"B-Average",employee_year!$B$2:$B$3801,"BBVA") -> 1.6416 | D8: =AVERAGEIFS(employee_year!U$2:U$3801,employee_year!$AD$2:$AD$3801,"C-Weak",employee_year!$B$2:$B$3801,"BBVA") -> 0.7804 | E8: =AVERAGEIFS(employee_year!U$2:U$3801,employee_year!$AD$2:$AD$3801,"Benchmark",employee_year!$B$2:$B$3801,"<>BBVA") -> 1.894
A9: Leadership trust (1–5) | B9: =AVERAGEIFS(employee_year!S$2:S$3801,employee_year!$AD$2:$AD$3801,"A-Strong",employee_year!$B$2:$B$3801,"BBVA") -> 4.5628 | C9: =AVERAGEIFS(employee_year!S$2:S$3801,employee_year!$AD$2:$AD$3801,"B-Average",employee_year!$B$2:$B$3801,"BBVA") -> 3.5508 | D9: =AVERAGEIFS(employee_year!S$2:S$3801,employee_year!$AD$2:$AD$3801,"C-Weak",employee_year!$B$2:$B$3801,"BBVA") -> 2.292 | E9: =AVERAGEIFS(employee_year!S$2:S$3801,employee_year!$AD$2:$AD$3801,"Benchmark",employee_year!$B$2:$B$3801,"<>BBVA") -> 3.63975
A10: Ethics score (0–10) | B10: =AVERAGEIFS(employee_year!L$2:L$3801,employee_year!$AD$2:$AD$3801,"A-Strong",employee_year!$B$2:$B$3801,"BBVA") -> 8.0929 | C10: =AVERAGEIFS(employee_year!L$2:L$3801,employee_year!$AD$2:$AD$3801,"B-Average",employee_year!$B$2:$B$3801,"BBVA") -> 6.4969 | D10: =AVERAGEIFS(employee_year!L$2:L$3801,employee_year!$AD$2:$AD$3801,"C-Weak",employee_year!$B$2:$B$3801,"BBVA") -> 4.5396 | E10: =AVERAGEIFS(employee_year!L$2:L$3801,employee_year!$AD$2:$AD$3801,"Benchmark",employee_year!$B$2:$B$3801,"<>BBVA") -> 6.583125
A11: Training completion (%) | B11: =AVERAGEIFS(employee_year!V$2:V$3801,employee_year!$AD$2:$AD$3801,"A-Strong",employee_year!$B$2:$B$3801,"BBVA") -> 84.7936 | C11: =AVERAGEIFS(employee_year!V$2:V$3801,employee_year!$AD$2:$AD$3801,"B-Average",employee_year!$B$2:$B$3801,"BBVA") -> 70.9375 | D11: =AVERAGEIFS(employee_year!V$2:V$3801,employee_year!$AD$2:$AD$3801,"C-Weak",employee_year!$B$2:$B$3801,"BBVA") -> 54.7319 | E11: =AVERAGEIFS(employee_year!V$2:V$3801,employee_year!$AD$2:$AD$3801,"Benchmark",employee_year!$B$2:$B$3801,"<>BBVA") -> 71.682875
A13: What to look for: every culture measure should be best in A-Strong, middling in B-Average and worst in C-Weak (for exit and turnover, “best” means lowest). That is exactly what happens - so the index moves the right way when culture changes. Only B-Average and the peer Benchmark are used in the statistical models.

Sheet lseg_observed
A1: REAL DATA. This is the only sheet with genuine numbers. Source: Refinitiv Public Companies dataset (public data on listed companies), retrieved June 2026. '—' = the bank does not disclose this figure.
A3: Panel 1 — Peer comparison, FY2025/FY0 (D&I and social indicators)
A4: Indicator | B4: BBVA | C4: Santander | D4: CaixaBank | E4: Sabadell | F4: Bankinter | G4: Unicaja
A5: D&I overall score (TRDIR) | B5: 64.75 | C5: 75.5 | D5: 64.25 | E5: 65 | F5: 62.75 | G5: 55.5
A6: Employee satisfaction (%) | B6: 90 | C6: 85 | D6: — | E6: 86.6 | F6: — | G6: —
A7: Women employees (%) | B7: 51.45 | C7: 52 | D7: 56.1 | E7: 54.65 | F7: 50.01 | G7: 54.2
A8: Women managers (%) | B8: 46.92 | C8: 39 | D8: 43.4 | E8: 42.3 | F8: 41.83 | G8: —
A9: Avg. training hours / employee | B9: 57.5 | C9: 24.9 | D9: 65.9 | E9: 22.5 | F9: 50 | G9: 64.69
A10: Training cost / employee (EUR) | B10: 495.4 | C10: — | D10: 334.7 | E10: 526 | F10: — | G10: 175.8
A11: Board gender diversity (%) | B11: 46.67 | C11: 40 | D11: 40 | E11: 40 | F11: 63.64 | G11: 42.86
A13: Panel 2 — BBVA time series (LSEG Social sheet)
A14: Indicator | B14: FY2023 | C14: FY2024 | D14: FY2025
A15: Employees (CSR reporting) | B15: 121486 | C15: 125916 | D15: 127174
A16: Employee satisfaction (%) | B16: 90.4 | C16: 89.2 | D16: 90
A17: Employee turnover (%) | B17: 11.8 | C17: 11.5 | D17: 11.8
A18: New jobs created (%) | B18: 5.02 | C18: 3.65 | D18: 1
A19: Gender pay-gap ratio (%) | B19: 99.5 | C19: 99.4 | D19: 99.7
A20: Avg. training hours / employee | B20: 48.82 | C20: 53.31 | D20: 57.5
A21: Total training hours (m) | B21: 5.931 | C21: 6.713 | D21: 7.245
A22: Total training cost (EUR m) | B22: 51.1 | C22: 63 | D22: 63
A23: Employees with disabilities (%) | B23: 0.73 | C23: 0.83 | D23: 0.92
A24: Lost days / million working days | B24: 314 | C24: 240 | D24: 240
A25: Social Pillar ESG score | B25: A | C25: A | D25: A
A26: ESG Controversies score | B26: A+ | C26: C− | D26: A+
A28: Panel 3 — Peer financials (LSEG 'other banks vs bbva' sheet) — inputs for Model 4
A29: Bank | B29: Market cap (EUR m) | C29: P/E (FY1) | D29: P/B (FY1) | E29: ROA (FY1, %) | F29: Dividend yield (%)
A30: BBVA | B30: 108872 | C30: 9.69 | D30: 1.83 | E30: 1.23 | F30: 4.74
A31: Santander | B31: 151213 | C31: 10.24 | D31: 1.4 | E31: 0.81 | F31: 2.26
A32: CaixaBank | B32: 79287 | C32: 12.73 | D32: 2.05 | E32: 0.92 | F32: 4.4
A33: Sabadell | B33: 14144 | C33: 9.3 | D33: 1.11 | E33: 0.68 | F33: 22.39
A34: Bankinter | B34: 12483 | C34: 10.8 | D34: 1.82 | E34: 0.87 | F34: 4.36
A35: Unicaja | B35: 7203 | C35: 11.24 | D35: 1.06 | E35: 0.64 | F35: 6.14
